{
  "type": "continuant",
  "voiced": true,
  "frames": [
    {
      "tone_formants": [
        {
          "freq": 253.21538228491235,
          "amp": 0.3554397814355381,
          "width": 0.01,
          "order": 4
        },
        {
          "freq": 412.1224121176753,
          "amp": 4.067174469609352,
          "width": 0.01,
          "order": 4
        },
        {
          "freq": 1141.259765625,
          "amp": 0.20933220464751479,
          "width": 0.01,
          "order": 4
        },
        {
          "freq": 1206.0057345653834,
          "amp": 0.22766831248072067,
          "width": 0.01,
          "order": 4
        },
        {
          "freq": 1501.4005008711551,
          "amp": 0.10852894024815096,
          "width": 0.01,
          "order": 4
        },
        {
          "freq": 2497.316029450328,
          "amp": 0.0021893997411784696,
          "width": 0.01,
          "order": 4
        },
        {
          "freq": 2949.800225749107,
          "amp": 0.0021307388356069166,
          "width": 0.01,
          "order": 4
        },
        {
          "freq": 3444.4190043546905,
          "amp": 0.002069024867455596,
          "width": 0.01,
          "order": 4
        },
        {
          "freq": 4100.714773795281,
          "amp": 0.001836463877136994,
          "width": 0.01,
          "order": 4
        },
        {
          "freq": 4973.569791193421,
          "amp": 0.0016233745603023376,
          "width": 0.01,
          "order": 4
        }
      ],
      "meta": {
        "toniness": {
          "energy": 2967.736015405506,
          "tone": 0.9784515634272325,
          "tone_amp": 1,
          "noise_amp": 0.0,
          "chaos": 0.0006034464952473801,
          "voiced": true
        },
        "tone_transfer": 0.04377456231712115,
        "noise_transfer": 0.0
      }
    }
  ],
  "meta": {
    "toniness": {
      "energy": 2967.736015405506,
      "tone": 0.9784515634272325,
      "tone_amp": 1,
      "noise_amp": 0.0,
      "chaos": 0.0006034464952473801,
      "voiced": true
    },
    "tone_transfer": 0.04377456231712115,
    "noise_transfer": 0.0
  }
}