{
  "type": "stop",
  "voiced": false,
  "duration": 5206,
  "frames": [
    {},
    {},
    {},
    {},
    {},
    {},
    {
      "meta": {
        "toniness": {
          "energy": 59.81241302937269,
          "tone": 0.6198258728163961,
          "tone_amp": 0,
          "noise_amp": 1.0,
          "chaos": 0.015710860911362395,
          "voiced": false
        },
        "noise_transfer": 0.13685066953716377
      },
      "noise_formants": [
        {
          "freq": 466.1564937838754,
          "amp": 0.4539378900344996,
          "width": 0.016,
          "order": 2
        },
        {
          "freq": 3962.109375,
          "amp": 3.7930038737014127,
          "width": 0.016,
          "order": 2
        },
        {
          "freq": 4463.65512203018,
          "amp": 2.9407734729927424,
          "width": 0.001,
          "order": 2
        },
        {
          "freq": 7293.472457170935,
          "amp": 1.2270653324996397,
          "width": 0.016,
          "order": 2
        },
        {
          "freq": 9344.43282438258,
          "amp": 1.5267146869622086,
          "width": 0.001,
          "order": 2
        },
        {
          "freq": 11208.472484671127,
          "amp": 0.43578629357857035,
          "width": 0.001,
          "order": 2
        },
        {
          "freq": 12401.72922056597,
          "amp": 0.24068897060062067,
          "width": 0.001,
          "order": 2
        },
        {
          "freq": 14110.372318050537,
          "amp": 0.21919583383878444,
          "width": 0.001,
          "order": 2
        },
        {
          "freq": 16597.714167636346,
          "amp": 0.11636115421639556,
          "width": 0.001,
          "order": 2
        },
        {
          "freq": 19000.0,
          "amp": 0,
          "width": 0.001,
          "order": 2
        }
      ]
    },
    {
      "meta": {
        "toniness": {
          "energy": 59.81241302937269,
          "tone": 0.6198258728163961,
          "tone_amp": 0,
          "noise_amp": 1.0,
          "chaos": 0.015710860911362395,
          "voiced": false
        },
        "noise_transfer": 0.10656527499202627
      },
      "noise_formants": [
        {
          "freq": 1981.0546875,
          "amp": 0.5741560407906141,
          "width": 0.016,
          "order": 2
        },
        {
          "freq": 3962.109375,
          "amp": 1.940601764410186,
          "width": 0.032,
          "order": 2
        },
        {
          "freq": 4864.858263923504,
          "amp": 1.8604661343775446,
          "width": 0.001,
          "order": 2
        },
        {
          "freq": 7636.058313920468,
          "amp": 1.462499306915112,
          "width": 0.016,
          "order": 2
        },
        {
          "freq": 9315.657813577363,
          "amp": 1.538448729942751,
          "width": 0.016,
          "order": 2
        },
        {
          "freq": 11000.0,
          "amp": 0,
          "width": 0.001,
          "order": 2
        },
        {
          "freq": 12887.55365896424,
          "amp": 0.22557585323659846,
          "width": 0.001,
          "order": 2
        },
        {
          "freq": 13991.669424940987,
          "amp": 0.14798103019943265,
          "width": 0.001,
          "order": 2
        },
        {
          "freq": 16320.827515826208,
          "amp": 0.06923786604805578,
          "width": 0.001,
          "order": 2
        },
        {
          "freq": 19080.372641350645,
          "amp": 0.003031794678702994,
          "width": 0.001,
          "order": 2
        }
      ]
    },
    {
      "meta": {
        "toniness": {
          "energy": 59.81241302937269,
          "tone": 0.6198258728163961,
          "tone_amp": 0,
          "noise_amp": 1.0,
          "chaos": 0.015710860911362395,
          "voiced": false
        },
        "noise_transfer": 0.07565572458746372
      },
      "noise_formants": [
        {
          "freq": 1981.0546875,
          "amp": 0.511244740935842,
          "width": 0.008,
          "order": 2
        },
        {
          "freq": 3962.1093749999995,
          "amp": 1.4035468843711072,
          "width": 0.032,
          "order": 2
        },
        {
          "freq": 4513.775769577232,
          "amp": 1.7066965920980606,
          "width": 0.016,
          "order": 2
        },
        {
          "freq": 7647.806505926629,
          "amp": 1.0404931596698177,
          "width": 0.001,
          "order": 2
        },
        {
          "freq": 9143.244818040692,
          "amp": 1.028370967369774,
          "width": 0.008,
          "order": 2
        },
        {
          "freq": 11028.785753852399,
          "amp": 0.2757140550776875,
          "width": 0.001,
          "order": 2
        },
        {
          "freq": 12900.689491219702,
          "amp": 0.15237182857639467,
          "width": 0.001,
          "order": 2
        },
        {
          "freq": 14081.633594179655,
          "amp": 0.1347421089359245,
          "width": 0.001,
          "order": 2
        },
        {
          "freq": 16206.263941732168,
          "amp": 0.07248627261716867,
          "width": 0.001,
          "order": 2
        },
        {
          "freq": 19000.0,
          "amp": 0,
          "width": 0.001,
          "order": 2
        }
      ]
    },
    {
      "meta": {
        "toniness": {
          "energy": 59.81241302937269,
          "tone": 0.6198258728163961,
          "tone_amp": 0,
          "noise_amp": 1.0,
          "chaos": 0.015710860911362395,
          "voiced": false
        },
        "noise_transfer": 0.030893837592199977
      },
      "noise_formants": [
        {
          "freq": 1981.0546875,
          "amp": 0.4815587700956433,
          "width": 0.016,
          "order": 2
        },
        {
          "freq": 3962.109375,
          "amp": 0.8947651025203058,
          "width": 0.032,
          "order": 2
        },
        {
          "freq": 4704.0021001226205,
          "amp": 1.197874429710439,
          "width": 0.016,
          "order": 2
        },
        {
          "freq": 7695.749211774825,
          "amp": 0.4444201758580498,
          "width": 0.001,
          "order": 2
        },
        {
          "freq": 9275.014307440566,
          "amp": 0.4261723171329647,
          "width": 0.001,
          "order": 2
        },
        {
          "freq": 11982.833071718173,
          "amp": 0.1674594646803532,
          "width": 0.001,
          "order": 2
        },
        {
          "freq": 13736.77583383467,
          "amp": 0.09958566452330853,
          "width": 0.001,
          "order": 2
        },
        {
          "freq": 14262.34085938637,
          "amp": 0.09909639554193478,
          "width": 0.001,
          "order": 2
        },
        {
          "freq": 16059.15830226541,
          "amp": 0.049473340967727625,
          "width": 0.001,
          "order": 2
        },
        {
          "freq": 18231.178495839766,
          "amp": 0.02688201640128772,
          "width": 0.001,
          "order": 2
        }
      ]
    }
  ],
  "meta": {
    "toniness": {
      "energy": 59.81241302937269,
      "tone": 0.6198258728163961,
      "tone_amp": 0,
      "noise_amp": 1.0,
      "chaos": 0.015710860911362395,
      "voiced": false
    }
  }
}