{
  "type": "continuant",
  "frames": [
    {
      "tone_formants": [
        {
          "freq": 198.71225317573587,
          "amp": 5.609437617694117,
          "width": 0.01,
          "order": 4
        },
        {
          "freq": 531.0,
          "amp": 0.0,
          "width": 0.01,
          "order": 4
        },
        {
          "freq": 601.9755837607092,
          "amp": 18.622300268470937,
          "width": 0.01,
          "order": 4
        },
        {
          "freq": 606.0,
          "amp": 0.0,
          "width": 0.01,
          "order": 4
        },
        {
          "freq": 706.0,
          "amp": 0.0,
          "width": 0.01,
          "order": 4
        },
        {
          "freq": 981.0,
          "amp": 0.0,
          "width": 0.01,
          "order": 4
        },
        {
          "freq": 1119.8474315778456,
          "amp": 2.1345548015780627,
          "width": 0.01,
          "order": 4
        },
        {
          "freq": 1156.0,
          "amp": 0.0,
          "width": 0.01,
          "order": 4
        },
        {
          "freq": 1356.0,
          "amp": 0.0,
          "width": 0.01,
          "order": 4
        },
        {
          "freq": 1948.7548828125,
          "amp": 0.001781511121377856,
          "width": 0.01,
          "order": 4
        },
        {
          "freq": 2212.1024560611363,
          "amp": 0.4055560432798135,
          "width": 0.01,
          "order": 4
        },
        {
          "freq": 2333.8462863716545,
          "amp": 0.6715665734153012,
          "width": 0.01,
          "order": 4
        },
        {
          "freq": 2810.0830078125,
          "amp": 0.14317702191458828,
          "width": 0.01,
          "order": 4
        },
        {
          "freq": 2986.202637981838,
          "amp": 0.32426199080697443,
          "width": 0.01,
          "order": 4
        },
        {
          "freq": 3081.0,
          "amp": 0.0,
          "width": 0.01,
          "order": 4
        },
        {
          "freq": 3780.6334987745468,
          "amp": 0.03878475956039148,
          "width": 0.01,
          "order": 4
        },
        {
          "freq": 3856.0,
          "amp": 0.0,
          "width": 0.01,
          "order": 4
        },
        {
          "freq": 4714.7486709948935,
          "amp": 0.0029301161225260565,
          "width": 0.01,
          "order": 4
        },
        {
          "freq": 5082.8450765385505,
          "amp": 0.12976394975221459,
          "width": 0.01,
          "order": 4
        },
        {
          "freq": 5648.288384595031,
          "amp": 0.12222135301612425,
          "width": 0.01,
          "order": 4
        }
      ],
      "meta": {
        "toniness": {
          "energy": 7922.965531725436,
          "tone": 0.9793340104377816,
          "tone_amp": 1,
          "noise_amp": 0.0,
          "chaos": 0.00036123661275499407,
          "voiced": true
        },
        "tone_transfer": 1.0000000000000022,
        "noise_transfer": 0.0
      }
    }
  ],
  "meta": {
    "toniness": {
      "energy": 7922.965531725436,
      "tone": 0.9793340104377816,
      "tone_amp": 1,
      "noise_amp": 0.0,
      "chaos": 0.00036123661275499407,
      "voiced": true
    },
    "tone_transfer": 1.0000000000000022,
    "noise_transfer": 0.0
  }
}