{
  "type": "continuant",
  "frames": [
    {
      "formants": [
        {
          "freq": 10.7666015625,
          "amp": 0.11562715020384703
        },
        {
          "freq": 102.28271484375,
          "amp": 1.3863376867480313
        },
        {
          "freq": 2255.60302734375,
          "amp": 0.08886048558966779
        },
        {
          "freq": 11837.87841796875,
          "amp": 0.08952535938291348
        },
        {
          "freq": 11988.61083984375,
          "amp": 0.07833026401209733
        }
      ],
      "tone_amp": 0.04602286874142767,
      "noise_amp": 0.024321919987910178
    }
  ]
}