{
  "type": "continuant",
  "frames": [
    {
      "tone_formants": [
        {
          "freq": 290.6982421875,
          "amp": 2.7919768394494104,
          "width": 0.005
        },
        {
          "freq": 785.9619140625,
          "amp": 0.8380472069236324,
          "width": 0.005
        },
        {
          "freq": 6330.76171875,
          "amp": 0.01702884850793188,
          "width": 0.01
        },
        {
          "freq": 8731.7138671875,
          "amp": 0.017071940544854922,
          "width": 0.01
        },
        {
          "freq": 9151.611328125,
          "amp": 0.018395325181609485,
          "width": 0.01
        }
      ]
    }
  ]
}